<?xml version="1.0" encoding="UTF-8"?>
<!DOCTYPE mapper PUBLIC "-//mybatis.org//DTD Mapper 3.0//EN" "http://mybatis.org/dtd/mybatis-3-mapper.dtd">
<mapper namespace="com.sweetpotatoclock.dao.AchieveListMapper">
  <resultMap id="BaseResultMap" type="com.sweetpotatoclock.entity.AchieveList">
    <!--
      WARNING - @mbg.generated
      This element is automatically generated by MyBatis Generator, do not modify.
    -->
    <result column="user_id" jdbcType="VARCHAR" property="userId" />
    <result column="achieve_id" jdbcType="INTEGER" property="achieveId" />
  </resultMap>
  <insert id="insert" parameterType="com.sweetpotatoclock.entity.AchieveList">
    <!--
      WARNING - @mbg.generated
      This element is automatically generated by MyBatis Generator, do not modify.
    -->
    insert into achieve_list (user_id, achieve_id)
    values (#{userId,jdbcType=VARCHAR}, #{achieveId,jdbcType=INTEGER})
  </insert>
  <select id="selectAll" resultMap="BaseResultMap">
    <!--
      WARNING - @mbg.generated
      This element is automatically generated by MyBatis Generator, do not modify.
    -->
    select user_id, achieve_id
    from achieve_list
  </select>
  <select id="selectAchieveListByUserId" parameterType="String" resultMap="BaseResultMap">
    <!--
      WARNING - @mbg.generated
      This element is automatically generated by MyBatis Generator, do not modify.
    -->
    select achieve_id
    from achieve_list
    where user_id=#{userId}
  </select>
</mapper>